{
    "Ar36": {
        "error": 0.00018877378817708443,
        "error_type": "SEM",
        "filter_outliers_dict": {
            "filter_outliers": true,
            "iterations": 1,
            "std_devs": 2
        },
        "fit": "Parabolic",
        "fn": 375,
        "include_baseline_error": false,
        "n": 400,
        "reviewed": true,
        "value": 0.002569362216403752
    },
    "Ar37": {
        "error": 0.021668899351662788,
        "error_type": "SEM",
        "filter_outliers_dict": {
            "filter_outliers": true,
            "iterations": 1,
            "std_devs": 2
        },
        "fit": "Parabolic",
        "fn": 379,
        "include_baseline_error": false,
        "n": 400,
        "reviewed": true,
        "value": -0.16389509284027015
    },
    "Ar38": {
        "error": 0.0039825044038566525,
        "error_type": "SEM",
        "filter_outliers_dict": {
            "filter_outliers": true,
            "iterations": 1,
            "std_devs": 2
        },
        "fit": "Linear",
        "fn": 375,
        "include_baseline_error": false,
        "n": 400,
        "reviewed": true,
        "value": -0.08110496694429409
    },
    "Ar39": {
        "error": 0.015642378887331044,
        "error_type": "SEM",
        "filter_outliers_dict": {
            "filter_outliers": true,
            "iterations": 1,
            "std_devs": 2
        },
        "fit": "Linear",
        "fn": 380,
        "include_baseline_error": false,
        "n": 400,
        "reviewed": true,
        "value": -0.02326017128309086
    },
    "Ar40": {
        "error": 0.020854947341601374,
        "error_type": "SEM",
        "filter_outliers_dict": {
            "filter_outliers": true,
            "iterations": 1,
            "std_devs": 2
        },
        "fit": "Parabolic",
        "fn": 383,
        "include_baseline_error": false,
        "n": 400,
        "reviewed": true,
        "value": 0.12044320643331438
    }
}