{
    "Ar36": {
        "error": 0.00013463033108564648,
        "error_type": "SEM",
        "filter_outliers_dict": {
            "filter_outliers": true,
            "iterations": 1,
            "std_devs": 3,
            "use_iqr_filtering": false,
            "use_standard_deviation_filtering": false
        },
        "fit": "linear",
        "fn": 398,
        "include_baseline_error": true,
        "n": 400,
        "outlier_excluded": [
            280,
            354
        ],
        "reviewed": true,
        "user_excluded": [],
        "value": 0.0028828864659873918
    },
    "Ar37": {
        "error": 0.013699590004743049,
        "error_type": "SEM",
        "filter_outliers_dict": {
            "filter_outliers": true,
            "iterations": 1,
            "std_devs": 3,
            "use_iqr_filtering": false,
            "use_standard_deviation_filtering": false
        },
        "fit": "linear",
        "fn": 399,
        "include_baseline_error": true,
        "n": 400,
        "outlier_excluded": [
            323
        ],
        "reviewed": true,
        "user_excluded": [],
        "value": -0.1808172132233062
    },
    "Ar38": {
        "error": 0.005096192494857761,
        "error_type": "SEM",
        "filter_outliers_dict": {
            "filter_outliers": true,
            "iterations": 1,
            "std_devs": 3,
            "use_iqr_filtering": false,
            "use_standard_deviation_filtering": false
        },
        "fit": "linear",
        "fn": 398,
        "include_baseline_error": true,
        "n": 400,
        "outlier_excluded": [
            40,
            396
        ],
        "reviewed": true,
        "user_excluded": [],
        "value": -0.07576251224103722
    },
    "Ar39": {
        "error": 0.015705511085705268,
        "error_type": "SEM",
        "filter_outliers_dict": {
            "filter_outliers": true,
            "iterations": 1,
            "std_devs": 3,
            "use_iqr_filtering": false,
            "use_standard_deviation_filtering": false
        },
        "fit": "linear",
        "fn": 400,
        "include_baseline_error": true,
        "n": 400,
        "outlier_excluded": [],
        "reviewed": true,
        "user_excluded": [],
        "value": -0.03316400305129855
    },
    "Ar40": {
        "error": 0.022509853275690373,
        "error_type": "SEM",
        "filter_outliers_dict": {
            "filter_outliers": true,
            "iterations": 1,
            "std_devs": 3,
            "use_iqr_filtering": false,
            "use_standard_deviation_filtering": false
        },
        "fit": "parabolic",
        "fn": 399,
        "include_baseline_error": true,
        "n": 400,
        "outlier_excluded": [
            145
        ],
        "reviewed": true,
        "user_excluded": [],
        "value": 0.2185619614074884
    }
}